pihat_widget/__init__.py
pihat_widget/board.py
pihat_widget/entry.py
pihat_widget/image.py
pihat_widget/light.py
pihat_widget/segment.py
pihat_widget/images/0.png
pihat_widget/images/1.png
pihat_widget/images/2.png
pihat_widget/images/3.png
pihat_widget/images/4.png
pihat_widget/images/5.png
pihat_widget/images/6.png
pihat_widget/images/7-Segment-ASCII-All.png
pihat_widget/images/7.png
pihat_widget/images/8.png
pihat_widget/images/9.png
pihat_widget/images/__init__.py
pihat_widget/images/amber.png
pihat_widget/images/green.png
pihat_widget/images/off.png
pihat_widget/images/red.png
pihat_widget/images/redamber.png
test/__init__.py
test/testseg.py
pihat_widget-1.4.1.dist-info/METADATA
pihat_widget-1.4.1.dist-info/WHEEL
pihat_widget-1.4.1.dist-info/top_level.txt
pihat_widget-1.4.1.dist-info/RECORD
